TreeMethods/TreeBuild.py
TreeMethods/__init__.py
TreeMethods-1.0.3.dist-info/LICENSE
TreeMethods-1.0.3.dist-info/METADATA
TreeMethods-1.0.3.dist-info/WHEEL
TreeMethods-1.0.3.dist-info/top_level.txt
TreeMethods-1.0.3.dist-info/RECORD
