Metadata-Version: 2.1
Name: TreeMethods
Version: 1.0.3
Summary: Creating a neighbour joining tree.
Home-page: https://github.com/BradBalderson/TreeMethods
Author: Brad Balderson
Author-email: brad.balderson@uqconnect.edu.au
License: UNKNOWN
Platform: UNKNOWN
Classifier: Programming Language :: Python :: 3
Classifier: License :: OSI Approved :: MIT License
Classifier: Operating System :: OS Independent
Requires-Python: >=3.6
